kingghidorah/__init__.py
kingghidorah/api.py
kingghidorah/calls.py
kingghidorah/exceptions.py
kingghidorah/sanitizers.py
kingghidorah/utils.py
kingghidorah-0.1.2.dist-info/WHEEL
kingghidorah-0.1.2.dist-info/METADATA
kingghidorah-0.1.2.dist-info/RECORD
